planilha_cotacao/__init__.py
planilha_cotacao/leitura_dados.py
planilha_cotacao/relatorio.py
planilha_cotacao-0.1.dist-info/METADATA
planilha_cotacao-0.1.dist-info/WHEEL
planilha_cotacao-0.1.dist-info/top_level.txt
planilha_cotacao-0.1.dist-info/RECORD
