Metadata-Version: 2.1
Name: planilha_cotacao
Version: 0.1
Requires-Dist: pandas
